boomslag_api_response/__init__.py
boomslag_api_response/admin.py
boomslag_api_response/apps.py
boomslag_api_response/models.py
boomslag_api_response/pagination.py
boomslag_api_response/serializers.py
boomslag_api_response/tests.py
boomslag_api_response/views.py
boomslag_common_api_response-1.2.2.dist-info/LICENSE
boomslag_common_api_response-1.2.2.dist-info/METADATA
boomslag_common_api_response-1.2.2.dist-info/WHEEL
boomslag_common_api_response-1.2.2.dist-info/top_level.txt
boomslag_common_api_response-1.2.2.dist-info/RECORD
