Metadata-Version: 2.1
Name: boomslag_common_api_response
Version: 1.2.2
Summary: Standard APIReponse for Django Rest Framework
Home-page: https://boomslag.com
Author: Boomslag
Author-email: mail@boomslag.com
Maintainer-email: support@boomslag.com
License: MIT
Keywords: django djangorestframework common api response boomslag
Classifier: Environment :: Web Environment
Classifier: Framework :: Django
Classifier: Intended Audience :: Developers
Classifier: License :: OSI Approved :: MIT License
Classifier: Operating System :: OS Independent
Classifier: Programming Language :: Python :: 3
Classifier: Programming Language :: Python :: 3.5
Classifier: Programming Language :: Python :: 3.6
Classifier: Programming Language :: Python :: 3.7
Classifier: Programming Language :: Python :: 3.8
Classifier: Programming Language :: Python :: 3.9
Classifier: Topic :: Software Development :: Libraries :: Python Modules
License-File: LICENSE
